mywheel/__init__.py
mywheel/array_like.py
mywheel/bpqueue.py
mywheel/dllist.py
mywheel/map_adapter.py
mywheel/robin.py
mywheel-0.2.dist-info/licenses/LICENSE.txt
mywheel-0.2.dist-info/METADATA
mywheel-0.2.dist-info/WHEEL
mywheel-0.2.dist-info/top_level.txt
mywheel-0.2.dist-info/RECORD
